{"Opaque": "(adj) not translucent; not allowing light, hear, etc. to pass through; dark, dull, unclear or stupid", "Offset": "(v, n) counteract, compensate for (verb); a counterbalance (noun)", "Occult": "(n, adj, v) the supernatural (noun); pertaining to magic, astrology, etc.; mysterious, secret or hidden (adj); to hide, to shut off from view", "Optimal/Optimum": "(adj) best, most desirable or favorable", "Obsolete": "(adj) out of date, no longer in use", "Officious": "(adj) excessively eager in giving unwanted advice or intruding where one is not wanted; meddlesome, pushy", "Obviate": "(v) prevent, eliminate, or make unnecessary", "Obstinate": "(adj) stubborn or hard to control", "Offhand": "(adj) casual, informal; done without preparation or forethought; rude in a short way, brusque", "Onerous": "(adj) burdensome, oppressive, hard to endure"}