{"Entitlement": "(n) having the right to certain privileges; believing, sometimes without cause, that one deserves or has a right to certain privileges", "Erroneous": "(adj) mistaken, in error; improper, morally incorrect", "Erratic": "(adj) inconsistent, wandering, having no fixed course", "Erudite": "(adj) scholarly, knowledgeable; possessing a deep, often systematic, knowledge", "Enervate": "(v) weaken, tire", "Equitable": "(adj) fair, equal, just", "Enigma": "(n) puzzle, mystery, riddle; mysterious or contradictory person", "Ephemeral": "(adj) lasting only a short time, fleeting", "Enhance": "(v) raise to a higher value, desirability, etc.", "Enumerate": "(v) count or list; specify one-by-one"}