{"apostate": "Person who deserts a party, cause, religion, etc.", "antedate": "Be older than, precede in time; assign to an earlier date", "anodyne": "Medicine that relieves pain (noun); soothing, relieving pain (adj)", "annul": "Make void or null, cancel, abolish (usually of laws or other established rules)", "apprise": "Inform, give notice to", "analgesia": "Pain relief; inability to feel pain", "apostle": "Pioneer of a reform movement (originally, an early follower of Jesus)", "approbation": "Praise or approval, especially formal approval", "apposite": "Highly appropriate, suitable, or relevant", "antithetical": "Directly opposed, opposite; involving antithesis (the rhetorical act of placing two phrases opposite one another for contrast, as in love me or hate me)"}