{"ebullient": "Very enthusiastic, lively, excited; bubbling as though being boiled", "emaciate": "Make abnormally thin, cause to physically waste away", "dyspeptic": "Grumpy, pessimistic, irritable; suffering from dyspepsia (indigestion)", "egress": "An exit or the action of exiting", "echelon": "A level, rank or grade; the people at that level", "duplicity": "Deceit, double-dealing, acting in two different ways for the purpose of deception", "edify": "Uplift, enlighten, instruct or improve in a spiritual or moral way", "effigy": "Representation or image of a person, esp. a crude facsimile used to mock a hated person", "elegy": "Song or poem of sorrow, esp. for a deceased person", "effrontery": "Shameless; Boldness"}