{"prudent": "cautious, wise/ \u09b8\u09b0\u09cd\u09a4\u0995/ \u09ac\u09bf\u099a\u0995\u09cd\u09b7\u09a3/ \u09a6\u09c2\u09b0\u09a6\u09b0\u09cd\u09b6\u09c0/ \u09b8\u09c1\u09ac\u09bf\u09ac\u09c7\u099a\u0995", "surfeit": "superabundance, excess/ \u09af\u09c7 \u0995\u09cb\u09a8\u09cb \u09ac\u09b8\u09cd\u09a4\u09c1\u09b0, \u09ac\u09bf\u09b6\u09c7\u09b7\u09a4 \u0996\u09be\u09a6\u09cd\u09af \u0993 \u09aa\u09be\u09a8\u09c0\u09df\u09c7\u09b0 \u0986\u09a4\u09bf\u09b6\u09af\u09cd\u09af \u09ac\u09be \u09ac\u09be\u09b9\u09c1\u09b2\u09cd\u09af", "attenuated": "decreased/ weakened/ thinned/ \u0995\u09c3\u09b6 \u09ac\u09be \u09b6\u09c0\u09b0\u09cd\u09a3 \u0995\u09b0\u09be/ \u09b2\u0998\u09c1 \u09ac\u09be \u09b2\u09be\u0998\u09ac \u0995\u09b0\u09be", "ostensible": "seeming, pretend, outward/ (\u09af\u09c1\u0995\u09cd\u09a4\u09bf \u09b8\u09ae\u09cd\u09ac\u09a8\u09cd\u09a7\u09c7) \u09aa\u09cd\u09b0\u0995\u09c3\u09a4 \u0995\u09be\u09b0\u09a8 \u0997\u09cb\u09aa\u09a8 \u0995\u09b0\u09be\u09b0\u09be \u099a\u09c7\u09b7\u09cd\u099f\u09be\u09df \u0989\u09aa\u09b8\u09cd\u09a5\u09be\u09aa\u09a8 \u0995\u09b0\u09be/ \u09b2\u09cb\u0995\u09a6\u09c7\u0996\u09be\u09a8\u09cb/ \u09ac\u09be\u09b9\u09cd\u09af\u09a4 \u09aa\u09cd\u09b0\u09a4\u09c0\u09df\u09ae\u09be\u09a8/ \u0986\u09aa\u09be\u09a4", "ferment": "1. cause to undergo fermentation/ \u0997\u09be\u099c\u09bf\u09df\u09c7 \u09a4\u09cb\u09b2\u09be \u09ac\u09be \u09a4\u09c1\u09b2\u09a4\u09c7 \u09b8\u09be\u09b9\u09be\u09af\u09cd\u09af \u0995\u09b0\u09be/ 2. agitation, turmoil, uproar/ \u09b8\u09be\u09ae\u09be\u099c\u09bf\u0995; \u09b0\u09be\u099c\u09a8\u09c8\u09a4\u09bf\u0995 \u0989\u09a4\u09cd\u09a4\u09c7\u099c\u09a8\u09be \u0993 \u0986\u09a8\u09cd\u09a6\u09b2\u09a8\u09c7\u09b0 \u0985\u09ac\u09b8\u09cd\u09a5\u09be", "incumbent": "necessary (for someone) as a duty or responsibility; morally binding/ currently holding an office/ \u09a6\u09be\u09df\u09bf\u09a4\u09cd\u09ac, \u0985\u09ac\u09b6\u09cd\u09af \u0995\u09b0\u09cd\u09a4\u09ac\u09cd\u09af/ \u0995\u09cb\u09a8\u09cb \u09aa\u09a6\u09c7 \u0985\u09a7\u09bf\u09b7\u09cd\u09a0\u09bf\u09a4 \u09ac\u09cd\u09af\u0995\u09cd\u09a4\u09bf/ \u09aa\u09a6\u09a7\u09bf\u0995\u09be\u09b0\u09c0", "efficacy": "power to produce an effect/ \u09ab\u09b2\u09aa\u09cd\u09b0\u09b8\u09c2\u09a4\u09be", "lassitude": "fatigue, weariness/ \u0985\u09ac\u09b8\u09a8\u09cd\u09a8\u09a4\u09be/ \u09a8\u09bf\u09b8\u09cd\u09a4\u09c7\u099c \u09ad\u09be\u09ac/ \u0995\u09cd\u09b2\u09be\u09a8\u09cd\u09a4\u09ad\u09be\u09ac", "deleterious": "harmful, bad/ \u0995\u09cd\u09b7\u09a4\u09bf\u0995\u09b0/ \u0995\u09cd\u09b7\u09a4\u09bf\u0995\u09be\u09b0\u0995/ \u0985\u09aa\u0995\u09be\u09b0\u0995", "strident": "unpleasantly loud and harsh/ rough, harsh, shrill/ \u0995\u0995\u09b0\u09cd\u09b6 \u0993 \u0995\u09b0\u09cd\u09a3\u09aa\u09c0\u09dc\u09be\u09a6\u09be\u09df\u0995", "fervid": "enthusiastic, passionate, intense/ \u09a4\u09aa\u09cd\u09a4/ \u0989\u09a6\u09cd\u09a6\u09c0\u09aa\u09cd\u09a4/ \u0990\u0995\u09be\u09a8\u09cd\u09a4\u09bf\u0995", "arbiter": "someone chosen to judge and decide a disputed issue/ someone with the power to settle matters at will", "dissent": "protest, differ, disagree/ \u09ad\u09bf\u09a8\u09cd\u09a8\u09ae\u09a4 \u09aa\u09c7\u09be\u09b7\u09a3 \u0995\u09b0\u09be/ \u09ad\u09bf\u09a8\u09cd\u09a8\u09ae\u09a4\u09c7\u09b0 \u09aa\u09cd\u09b0\u0995\u09be\u09b6", "propagate": "multiply, spread, produce/ \u09e7 \u09b8\u09cd\u09ac\u09be\u09ad\u09be\u09ac\u09bf\u0995 \u09aa\u09cd\u09b0\u0995\u09cd\u09b0\u09bf\u09df\u09be\u09df (\u0989\u09a6\u09cd\u09ad\u09bf\u09a6, \u09aa\u09cd\u09b0\u09be\u09a3\u09c0, \u09ac\u09cd\u09af\u09be\u09a7\u09bf \u0987\u09a4\u09cd\u09af\u09be\u09a6\u09bf) \u09b8\u0982\u0996\u09cd\u09af\u09be\u09ac\u09c3\u09a6\u09cd\u09a7\u09bf \u0995\u09b0\u09be/ \u09ac\u0982\u09b6\u09ac\u09c3\u09a6\u09cd\u09a7\u09bf \u09ac\u09be \u09ac\u09bf\u09b8\u09cd\u09a4\u09be\u09b0 \u0995\u09b0\u09be \u09e8 \u09ac\u09cd\u09af\u09be\u09aa\u0995\u09ad\u09be\u09ac\u09c7 \u09aa\u09cd\u09b0\u099a\u09be\u09b0 \u0995\u09b0\u09be/ \u09ac\u09bf\u09b8\u09cd\u09a4\u09be\u09b0 \u0995\u09b0\u09be", "spurious": "counterfeit, false, specious/ \u09ae\u09c7\u0995\u09bf/ \u09ae\u09bf\u09a5\u09cd\u09af\u09be/ \u099c\u09be\u09b2/ \u09ad\u09c7\u099c\u09be\u09b2", "milieu": "setting, the environmental condition/ \u09aa\u09be\u09b0\u09bf\u09aa\u09be\u09b0\u09cd\u09b6\u09cd\u09ac\u09bf\u0995 \u0985\u09ac\u09b8\u09cd\u09a5\u09be/ \u09b8\u09be\u09ae\u09be\u099c\u09bf\u0995 \u09aa\u09be\u09b0\u09bf\u09aa\u09be\u09b0\u09cd\u09b6\u09cd\u09ac\u09bf\u0995\u09a4\u09be", "innocuous": "mild/ not harmful or injurious/ harmless/ \u0985\u09a8\u09aa\u0995\u09be\u09b0\u09c0/ \u09a8\u09bf\u09b0\u09cd\u09ac\u09bf\u09b7", "heresy": "lack of faith, dissent, unbelief/ \u09aa\u09cd\u09b0\u099a\u09b2\u09bf\u09a4 \u09ae\u09a4\u09c7\u09b0 \u09ac\u09bf\u09b0\u09c1\u09a6\u09cd\u09a7\u09c7 \u09ac\u09bf\u09b6\u09cd\u09ac\u09be\u09b8 (\u09ac\u09bf\u09b6\u09c7\u09b7\u09a4 \u09a7\u09b0\u09cd\u09ae \u09ac\u09bf\u09b6\u09cd\u09ac\u09be\u09b8)", "concomitant": "(adj) Occurring or existing concurrently; attendant/ \u09b8\u09b9\u0997\u09be\u09ae\u09c0 \u09ac\u09be \u0986\u09a8\u09c1\u09b7\u0999\u09cd\u0997\u09bf\u0995/ \u09b8\u09b9\u09ac\u09bf\u09a6\u09cd\u09af\u09ae\u09be\u09a8/ (n) One that occurs or exists concurrently with another/ \u09b8\u0999\u09cd\u0997\u09c0 \u09ac\u09be \u0986\u09a8\u09c1\u09b7\u0999\u09cd\u0997\u09bf\u0995 \u09ac\u09b8\u09cd\u09a4\u09c1/ \u09b8\u09b9\u09ac\u09bf\u09a6\u09cd\u09af\u09ae\u09be\u09a8 \u09ac\u09cd\u09af\u0995\u09cd\u09a4\u09bf \u09ac\u09be \u09ac\u09b8\u09cd\u09a4\u09c1", "anomaly": "abnormality, irregularity/ \u0985\u09b8\u09cd\u09ac\u09be\u09ad\u09be\u09ac\u09bf\u0995 \u09ac\u09be \u09ac\u09cd\u09af\u09a4\u09bf\u0995\u09cd\u09b0\u09ae\u09c0 \u09ac\u09b8\u09cd\u09a4\u09c1"}